FSM_Challenge/FeatureEngineering.py
FSM_Challenge/TimeSeriesModelEvaluator.py
FSM_Challenge/__init__.py
FSM_Challenge/utils.py
FSM_Challenge-1.0.1.dist-info/METADATA
FSM_Challenge-1.0.1.dist-info/WHEEL
FSM_Challenge-1.0.1.dist-info/top_level.txt
FSM_Challenge-1.0.1.dist-info/RECORD
