Metadata-Version: 2.1
Name: FSM_Challenge
Version: 1.0.1
Requires-Dist: cloudpickle==3.1.0
Requires-Dist: contourpy==1.3.0
Requires-Dist: cycler==0.12.1
Requires-Dist: fonttools==4.55.0
Requires-Dist: importlib-resources==6.4.5
Requires-Dist: joblib==1.4.2
Requires-Dist: kiwisolver==1.4.7
Requires-Dist: llvmlite==0.43.0
Requires-Dist: matplotlib==3.9.3
Requires-Dist: networkx==3.2.1
Requires-Dist: numba==0.60.0
Requires-Dist: numpy==2.0.2
Requires-Dist: packaging==24.2
Requires-Dist: pandas==2.2.3
Requires-Dist: pillow==11.0.0
Requires-Dist: pyparsing==3.2.0
Requires-Dist: python-dateutil==2.9.0.post0
Requires-Dist: pytz==2024.2
Requires-Dist: scikit-learn==1.5.2
Requires-Dist: scipy==1.13.1
Requires-Dist: shap==0.46.0
Requires-Dist: six==1.16.0
Requires-Dist: slicer==0.0.8
Requires-Dist: threadpoolctl==3.5.0
Requires-Dist: tqdm==4.67.1
Requires-Dist: tzdata==2024.2
Requires-Dist: zipp==3.21.0
